recommenders/__init__.py
recommenders/datasets/__init__.py
recommenders/datasets/amazon_reviews.py
recommenders/datasets/cosmos_cli.py
recommenders/datasets/covid_utils.py
recommenders/datasets/criteo.py
recommenders/datasets/download_utils.py
recommenders/datasets/mind.py
recommenders/datasets/movielens.py
recommenders/datasets/pandas_df_utils.py
recommenders/datasets/python_splitters.py
recommenders/datasets/spark_splitters.py
recommenders/datasets/sparse.py
recommenders/datasets/split_utils.py
recommenders/datasets/wikidata.py
recommenders/evaluation/__init__.py
recommenders/evaluation/python_evaluation.py
recommenders/evaluation/spark_evaluation.py
recommenders/models/__init__.py
recommenders/models/cornac/__init__.py
recommenders/models/cornac/cornac_utils.py
recommenders/models/deeprec/__init__.py
recommenders/models/deeprec/deeprec_utils.py
recommenders/models/deeprec/DataModel/ImplicitCF.py
recommenders/models/deeprec/DataModel/__init__.py
recommenders/models/deeprec/io/__init__.py
recommenders/models/deeprec/io/dkn_item2item_iterator.py
recommenders/models/deeprec/io/dkn_iterator.py
recommenders/models/deeprec/io/iterator.py
recommenders/models/deeprec/io/nextitnet_iterator.py
recommenders/models/deeprec/io/sequential_iterator.py
recommenders/models/deeprec/models/__init__.py
recommenders/models/deeprec/models/base_model.py
recommenders/models/deeprec/models/dkn.py
recommenders/models/deeprec/models/dkn_item2item.py
recommenders/models/deeprec/models/xDeepFM.py
recommenders/models/deeprec/models/graphrec/__init__.py
recommenders/models/deeprec/models/graphrec/lightgcn.py
recommenders/models/deeprec/models/sequential/__init__.py
recommenders/models/deeprec/models/sequential/asvd.py
recommenders/models/deeprec/models/sequential/caser.py
recommenders/models/deeprec/models/sequential/gru.py
recommenders/models/deeprec/models/sequential/nextitnet.py
recommenders/models/deeprec/models/sequential/rnn_cell_implement.py
recommenders-1.2.1.dist-info/AUTHORS.md
recommenders-1.2.1.dist-info/LICENSE
recommenders-1.2.1.dist-info/METADATA
recommenders-1.2.1.dist-info/WHEEL
recommenders-1.2.1.dist-info/top_level.txt
recommenders-1.2.1.dist-info/RECORD
