Metadata-Version: 2.1
Name: recommenders
Version: 1.2.1
Summary: Recommenders - Python utilities for building recommendation systems
Home-page: https://github.com/recommenders-team/recommenders
Author: Recommenders contributors
Author-email: recommenders-technical-discuss@lists.lfaidata.foundation
Project-URL: Documentation, https://recommenders-team.github.io/recommenders/intro.html
Project-URL: Wiki, https://github.com/recommenders-team/recommenders/wiki
Keywords: recommendations recommendation recommenders recommender system engine machine learning python spark gpu
Classifier: Development Status :: 5 - Production/Stable
Classifier: Intended Audience :: Developers
Classifier: Intended Audience :: Information Technology
Classifier: Intended Audience :: Science/Research
Classifier: Topic :: Scientific/Engineering :: Artificial Intelligence
Classifier: Topic :: Software Development :: Libraries :: Python Modules
Classifier: License :: OSI Approved :: MIT License
Classifier: Programming Language :: Python :: 3.8
Classifier: Programming Language :: Python :: 3.9
Classifier: Programming Language :: Python :: 3.10
Classifier: Programming Language :: Python :: 3.11
Classifier: Operating System :: POSIX :: Linux
Requires-Python: >=3.6
License-File: LICENSE
License-File: AUTHORS.md
Requires-Dist: category-encoders<3,>=2.6.0
Requires-Dist: cornac<3,>=1.15.2
Requires-Dist: hyperopt<1,>=0.2.7
Requires-Dist: lightgbm<5,>=4.0.0
Requires-Dist: locust<3,>=2.12.2
Requires-Dist: memory-profiler<1,>=0.61.0
Requires-Dist: nltk<4,>=3.8.1
Requires-Dist: notebook<8,>=6.5.5
Requires-Dist: numba<1,>=0.57.0
Requires-Dist: pandas<3.0.0,>2.0.0
Requires-Dist: retrying<2,>=1.3.4
Requires-Dist: scikit-learn<2,>=1.2.0
Requires-Dist: scikit-surprise>=1.1.3
Requires-Dist: seaborn<1,>=0.13.0
Requires-Dist: transformers<5,>=4.27.0
Requires-Dist: pandera[strategies]<0.18,>=0.6.5; python_version <= "3.8"
Requires-Dist: statsmodels<=0.14.1; python_version <= "3.8"
Requires-Dist: pandera[strategies]>=0.15.0; python_version >= "3.9"
Requires-Dist: statsmodels>=0.14.4; python_version >= "3.9"
Provides-Extra: all
Requires-Dist: tf-slim>=1.1.0; extra == "all"
Requires-Dist: black>=23.3.0; extra == "all"
Requires-Dist: fastai<3,>=2.7.11; extra == "all"
Requires-Dist: tensorflow!=2.10.0.*,!=2.9.0.*,!=2.9.1,!=2.9.2,<2.16,>=2.8.4; extra == "all"
Requires-Dist: pyspark<=4,>=3.3.0; extra == "all"
Requires-Dist: pytest-mock>=3.10.0; extra == "all"
Requires-Dist: pyarrow>=10.0.1; extra == "all"
Requires-Dist: nvidia-ml-py>=11.525.84; extra == "all"
Requires-Dist: pytest>=7.2.1; extra == "all"
Requires-Dist: pytest-cov>=4.1.0; extra == "all"
Requires-Dist: torch<3,>=2.0.1; extra == "all"
Requires-Dist: spacy<=3.7.5; python_version <= "3.8" and extra == "all"
Requires-Dist: numpy<1.25.0; python_version <= "3.8" and extra == "all"
Provides-Extra: dev
Requires-Dist: black>=23.3.0; extra == "dev"
Requires-Dist: pytest>=7.2.1; extra == "dev"
Requires-Dist: pytest-cov>=4.1.0; extra == "dev"
Requires-Dist: pytest-mock>=3.10.0; extra == "dev"
Provides-Extra: experimental
Requires-Dist: xlearn==0.40a1; extra == "experimental"
Requires-Dist: vowpalwabbit<9,>=8.9.0; extra == "experimental"
Requires-Dist: nni==1.5; extra == "experimental"
Requires-Dist: pymanopt>=0.2.5; extra == "experimental"
Requires-Dist: lightfm<2,>=1.17; extra == "experimental"
Provides-Extra: gpu
Requires-Dist: fastai<3,>=2.7.11; extra == "gpu"
Requires-Dist: nvidia-ml-py>=11.525.84; extra == "gpu"
Requires-Dist: tensorflow!=2.10.0.*,!=2.9.0.*,!=2.9.1,!=2.9.2,<2.16,>=2.8.4; extra == "gpu"
Requires-Dist: tf-slim>=1.1.0; extra == "gpu"
Requires-Dist: torch<3,>=2.0.1; extra == "gpu"
Requires-Dist: numpy<1.25.0; python_version <= "3.8" and extra == "gpu"
Requires-Dist: spacy<=3.7.5; python_version <= "3.8" and extra == "gpu"
Provides-Extra: spark
Requires-Dist: pyarrow>=10.0.1; extra == "spark"
Requires-Dist: pyspark<=4,>=3.3.0; extra == "spark"
